CHANGES.rst
CONTRIBUTORS.rst
DEVELOP.rst
LICENSE.rst
MANIFEST.in
README.rst
setup.cfg
setup.py
docs/conf.py
docs/index.rst
src/collective/__init__.py
src/collective.sortedcontrolpanels.egg-info/PKG-INFO
src/collective.sortedcontrolpanels.egg-info/SOURCES.txt
src/collective.sortedcontrolpanels.egg-info/dependency_links.txt
src/collective.sortedcontrolpanels.egg-info/entry_points.txt
src/collective.sortedcontrolpanels.egg-info/namespace_packages.txt
src/collective.sortedcontrolpanels.egg-info/not-zip-safe
src/collective.sortedcontrolpanels.egg-info/requires.txt
src/collective.sortedcontrolpanels.egg-info/top_level.txt
src/collective/sortedcontrolpanels/__init__.py
src/collective/sortedcontrolpanels/configure.zcml
src/collective/sortedcontrolpanels/interfaces.py
src/collective/sortedcontrolpanels/patches.py
src/collective/sortedcontrolpanels/permissions.zcml
src/collective/sortedcontrolpanels/setuphandlers.py
src/collective/sortedcontrolpanels/testing.py
src/collective/sortedcontrolpanels/browser/__init__.py
src/collective/sortedcontrolpanels/browser/configure.zcml
src/collective/sortedcontrolpanels/browser/overrides/.gitkeep
src/collective/sortedcontrolpanels/browser/static/.gitkeep
src/collective/sortedcontrolpanels/locales/README.rst
src/collective/sortedcontrolpanels/locales/__init__.py
src/collective/sortedcontrolpanels/locales/collective.sortedcontrolpanels.pot
src/collective/sortedcontrolpanels/locales/update.py
src/collective/sortedcontrolpanels/locales/update.sh
src/collective/sortedcontrolpanels/locales/en/LC_MESSAGES/collective.sortedcontrolpanels.po
src/collective/sortedcontrolpanels/profiles/default/browserlayer.xml
src/collective/sortedcontrolpanels/profiles/default/catalog.xml
src/collective/sortedcontrolpanels/profiles/default/metadata.xml
src/collective/sortedcontrolpanels/profiles/default/registry.xml
src/collective/sortedcontrolpanels/profiles/default/rolemap.xml
src/collective/sortedcontrolpanels/profiles/uninstall/browserlayer.xml
src/collective/sortedcontrolpanels/tests/__init__.py
src/collective/sortedcontrolpanels/tests/test_robot.py
src/collective/sortedcontrolpanels/tests/test_setup.py
src/collective/sortedcontrolpanels/tests/robot/test_example.robot